tron_energy/__init__.py
tron_energy/async_tron_energy.py
tron_energy/tron_energy.py
tron_energy/version.py
Tron_Energy-0.2.1.dist-info/LICENSE
Tron_Energy-0.2.1.dist-info/METADATA
Tron_Energy-0.2.1.dist-info/WHEEL
Tron_Energy-0.2.1.dist-info/top_level.txt
Tron_Energy-0.2.1.dist-info/RECORD
