Metadata-Version: 2.1
Name: Tron-Energy
Version: 0.2.1
Summary: A simple package to simplify interfacing with tron energy lending RESTful API
Author-email: Ephraim <ephraimakolo2017@gmail.com>
License: MIT
Project-URL: homepage, https://itrx.io/
Project-URL: repository, https://github.com/Ephraim-Akolo/Tron-Energy
Keywords: TRON-ENERGY,tronenergy
Classifier: Topic :: Software Development :: Libraries :: Python Modules
Classifier: Development Status :: 2 - Pre-Alpha
Classifier: Intended Audience :: Developers
Classifier: Natural Language :: English
Requires-Python: <4.0,>=3.7
License-File: LICENSE
Requires-Dist: requests<3,>=2
Requires-Dist: aiohttp<4,>=3
